src/myCPU.v
module myCPU (
// ============================================================================
// myCPU.v   (Heavily commented / educational version)
// ----------------------------------------------------------------------------
// A minimalistic custom CPU with:
//
//   • 16 general-purpose 8-bit registers (pregs[0..15])
//   • 16-bit program counter (PCH:PCL)
//   • 8-bit instruction register (IR)
//   • 16-bit pointer register (POINTERH:POINTERL)
//   • simple fetch → decode → optional memory → execute micro-phases
//   • instructions encoded inside DI[2:0] (3-bit opcode)
//   • optional register index in DI[7:4]
//
// The CPU performs **one instruction fetch per two cycles**:
//
//   OP_FETCH1 → OP_FETCH2 → (optional memory phase) → OP_FETCH1...
//
// Memory interface:
//   AB  = 16-bit address bus
//   DI  = 8-bit data input from memory
//   DO  = 8-bit data output to memory
//   RW  = read(0) or write(1)
//
// This version includes EXCESSIVE comments for maximum clarity.
// ============================================================================ss
    // CPU clock and reset
    input  wire        CLK,      // rising-edge active clock
    input  wire        RESET,    // reset = initialize CPU

    // Memory interface
    input  wire [7:0]  DI,       // data read from memory
    output reg  [15:0] AB,       // address bus
    output reg  [7:0]  DO,       // data to memory (on write)
    output reg         RW        // READ=0, WRITE=1
);

// ============================================================================
// CPU MICRO-PHASE STATES
// These are *not* instructions — they are internal CPU pipeline microsteps.
// ============================================================================

parameter OP_FETCH1   = 8'h00;   // place PC on address bus, request memory read
parameter OP_FETCH2   = 8'h01;   // instruction arrives in DI → decode opcode
parameter OP_MEMREAD  = 8'h02;   // load register from memory
parameter OP_MEMWRITE = 8'h03;   // write register to memory

reg [2:0] phase;                 // current micro-phase

// ============================================================================
// CPU REGISTER FILE LAYOUT  (pregs[0..15])
// ============================================================================
// 16 8-bit registers. Index meanings:
//
//    0  = PCL        (program counter low byte)
//    1  = PCH        (program counter high byte)
//    2  = A          (accumulator)
//    3  = B
//    4  = C
//    5  = D
//    6  = POINTERL   (low byte of memory pointer)
//    7  = POINTERH   (high byte of memory pointer)
//    8  = STATUSL    (flags: Z, C, ...)
//    9  = STATUSH    (reserved)
//    A  = IR         (instruction register)
//    C  = JUMPL      (jump vector low)
//    D  = JUMPH      (jump vector high)
//    E  = E          (free)
//    F  = F          (free)
//
// Registers B–F are available to user code.
// ============================================================================

parameter regPCL       = 4'h0;
parameter regPCH       = 4'h1;
parameter regA         = 4'h2;
parameter regB         = 4'h3;
parameter regC         = 4'h4;
parameter regD         = 4'h5;
parameter regPOINTERL  = 4'h6;
parameter regPOINTERH  = 4'h7;
parameter regSTATUSL   = 4'h8;
parameter regSTATUSH   = 4'h9;
parameter regIR        = 4'hA;
parameter regJUMPL     = 4'hC;
parameter regJUMPH     = 4'hD;
parameter regE         = 4'hE;
parameter regF         = 4'hF;

// ============================================================================
// STATUS REGISTER BIT DEFINITIONS
// ---------------------------------------------------------------------------
// STATUSL bit 0 = Z  (Zero flag)
// STATUSL bit 1 = C  (Carry flag)
// ============================================================================

parameter statusRegZ   = 3'd0;
parameter statusRegC   = 3'd1;

// ============================================================================
// 16-entry register file
// ============================================================================

reg [7:0] pregs [0:15];      // 16 general-purpose registers

reg        carry;            // internal carry flag (not always used)
reg [8:0] sum9;
reg [7:0] tmp;
reg [3:0]  selectedReg;      // used for memory load target register

// ============================================================================
// Memory direction constants
// ============================================================================
parameter READ  = 1'b0;
parameter WRITE = 1'b1;

// ============================================================================
// OPCODE DEFINITIONS (3-bit opcode in DI[2:0])
// Leading upper nibble (DI[7:4]) often encodes a register index.
// ============================================================================

parameter INSTR_SET  = 3'h0;   // SET A = (next byte)
parameter INSTR_LD   = 3'h1;   // LDA: reg[DI[7:4]] = mem[pointer]
parameter INSTR_ST   = 3'h2;   // STA: mem[pointer] = reg[DI[7:4]]
parameter INSTR_AND  = 3'h3;   // A = A & R
parameter INSTR_ADD  = 3'h4;   // A = A + R (Z,C flags)
parameter INSTR_NOT  = 3'h5;   // R = ~R
parameter INSTR_JP   = 3'h6;   // if Z=1 then jump to {JUMPH,JUMPL}
parameter INSTR_CHG  = 3'h7;   // swap A ↔ R

integer i;

// ============================================================================
// MAIN CPU PROCESS
// Executes one micro-operation per clock.
// ============================================================================
always @(posedge CLK) begin

    // =========================================================================
    // RESET PHASE
    // =========================================================================
    if (RESET) begin
        // Clear all registers for deterministic startup
        
        pregs[0] <= 8'h00;
        pregs[1] <= 8'h00;
        pregs[2] <= 8'h00;
        pregs[3] <= 8'h00;
        pregs[4] <= 8'h00;
        pregs[5] <= 8'h00;
        pregs[6] <= 8'h00;
        pregs[8] <= 8'h00;
        pregs[9] <= 8'h00;
        pregs[10] <= 8'h00;
        pregs[11] <= 8'h00;
        pregs[12] <= 8'h00;
        pregs[13] <= 8'h00;
        pregs[14] <= 8'h00;
        pregs[15] <= 8'h00;


        // Start fetching from address 0x0000
        phase <= OP_FETCH1;

        // Initialize bus state
        AB    <= 16'h0000;
        DO    <= 8'h00;
        RW    <= READ;
        carry <= 1'b0;
        selectedReg <= 4'h0;
    end 
    else begin

        // =====================================================================
        // CPU MICRO-PHASE STATE MACHINE
        // =====================================================================
        case (phase)

        // =====================================================================
        // OP_FETCH1 — Place the PC on the address bus and request memory read
        // =====================================================================
        OP_FETCH1: begin
            AB <= {pregs[regPCH], pregs[regPCL]};  // address = PC
            RW <= READ;                            // request read
            phase <= OP_FETCH2;                    // next phase: fetch instruction
        end

        // =====================================================================
        // OP_FETCH2 — CPU receives instruction byte in DI
        // =====================================================================
        OP_FETCH2: begin
            pregs[regIR] <= DI;          // Store instruction byte into IR

            // Decode opcode (lower 3 bits)
            case (DI[2:0])

                // ---------------------------------------------------------------------
                // SET — Load immediate value into register A
                //   Format:    [ rrrr 0000 ]
                // ---------------------------------------------------------------------
                INSTR_SET: begin
                    selectedReg <= DI[7:4];    // load immediate selected reg
                    // Increase PC to next byte (the immediate)
                    {pregs[regPCH], pregs[regPCL]} <= 
                        {pregs[regPCH], pregs[regPCL]} + 16'd1;

                    // Memory read for the immediate byte
                    AB <= {pregs[regPCH], pregs[regPCL]} + 16'd1;
                    RW <= READ;
                    phase <= OP_MEMREAD;
                end

                // ---------------------------------------------------------------------
                // LDA — Load register from memory at pointer address
                // ---------------------------------------------------------------------
                INSTR_LD: begin
                    selectedReg <= DI[7:4];                // which register to load
                    AB <= {pregs[regPOINTERH], pregs[regPOINTERL]};
                    RW <= READ;
                    phase <= OP_MEMREAD;
                end

                // ---------------------------------------------------------------------
                // STA — Store register into memory at pointer address
                // ---------------------------------------------------------------------
                INSTR_ST: begin
                    AB <= {pregs[regPOINTERH], pregs[regPOINTERL]};
                    RW <= WRITE;
                    DO <= pregs[DI[7:4]];                  // write selected register
                    phase <= OP_MEMWRITE;
                end

                // ---------------------------------------------------------------------
                // AND — A = A & reg[R]
                // ---------------------------------------------------------------------
                INSTR_AND: begin
                    pregs[regA] <= pregs[regA] & pregs[DI[7:4]];
                    // Update Z flag
                    pregs[regSTATUSL][statusRegZ] <= 
                        ((pregs[regA] & pregs[DI[7:4]]) == 8'h00);
                    // Advance PC
                    {pregs[regPCH], pregs[regPCL]} <= 
                        {pregs[regPCH], pregs[regPCL]} + 16'd1;
                    phase <= OP_FETCH1;
                end

                // ---------------------------------------------------------------------
                // ADD — A = A + reg[R], update C,Z
                // ---------------------------------------------------------------------
                INSTR_ADD: begin
                    sum9 = {1'b0, pregs[regA]} + {1'b0, pregs[DI[7:4]]};
                    pregs[regA] <= sum9[7:0];
                    pregs[regSTATUSL][statusRegC] <= sum9[8];
                    pregs[regSTATUSL][statusRegZ] <= (sum9[7:0] == 8'h00);
                    {pregs[regPCH], pregs[regPCL]} <= 
                        {pregs[regPCH], pregs[regPCL]} + 16'd1;
                    phase <= OP_FETCH1;
                end

                // ---------------------------------------------------------------------
                // NOT — reg[R] = ~reg[R], update Z flag
                // ---------------------------------------------------------------------
                INSTR_NOT: begin
                    sum9[7:0] = ~pregs[DI[7:4]];
                    pregs[DI[7:4]] <= sum9[7:0];
                    pregs[regSTATUSL][statusRegZ] <= (sum9[7:0] == 8'h00);
                    {pregs[regPCH], pregs[regPCL]} <= 
                        {pregs[regPCH], pregs[regPCL]} + 16'd1;
                    phase <= OP_FETCH1;
                end
 
                // ------ ---------------------------------------------------------------
                // JPZ — Jump if status register bit is set/not set
                //    vbbb 0110 if status register bbb bit is v then branch
                // ---------------------------------------------------------------------
                INSTR_JP : begin
                    /*
                    if (pregs[regSTATUSL][statusRegZ]) begin
                        pregs[regPCL] <= pregs[regJUMPL];
                        pregs[regPCH] <= pregs[regJUMPH];
                    end
                    else begin
                        {pregs[regPCH], pregs[regPCL]} <= 
                            {pregs[regPCH], pregs[regPCL]} + 16'd1;
                    end
                    phase <= OP_FETCH1;
                    */
                    if (pregs[regSTATUSL][DI[6:4]] == DI[7]) begin
                        pregs[regPCL] <= pregs[regJUMPL];
                        pregs[regPCH] <= pregs[regJUMPH];
                    end
                    else begin
                        {pregs[regPCH], pregs[regPCL]} <= 
                            {pregs[regPCH], pregs[regPCL]} + 16'd1;
                    end
                    phase <= OP_FETCH1;                    
                    
                end

                // ---------------------------------------------------------------------
                // CHG — Swap A <-> reg[R]
                // ---------------------------------------------------------------------
                INSTR_CHG: begin
                    tmp = pregs[DI[7:4]];
                    pregs[DI[7:4]] <= pregs[regA];
                    pregs[regA] <= tmp;
                    {pregs[regPCH], pregs[regPCL]} <= 
                        {pregs[regPCH], pregs[regPCL]} + 16'd1;
                    phase <= OP_FETCH1;
                end

                // ---------------------------------------------------------------------
                // DEFAULT — Undefined opcode → treat as NOP
                // ---------------------------------------------------------------------
                default: begin
                    {pregs[regPCH], pregs[regPCL]} <= 
                        {pregs[regPCH], pregs[regPCL]} + 16'd1;
                    phase <= OP_FETCH1;
                end
            endcase
        end // OP_FETCH2

        // =====================================================================
        // OP_MEMREAD — Data from memory is in DI → store into selectedReg
        // =====================================================================
        OP_MEMREAD: begin
            pregs[selectedReg] <= DI;
            {pregs[regPCH], pregs[regPCL]} <= 
                {pregs[regPCH], pregs[regPCL]} + 16'd1;
            phase <= OP_FETCH1;
        end

        // =====================================================================
        // OP_MEMWRITE — Write was already issued; just advance PC
        // =====================================================================
        OP_MEMWRITE: begin
            {pregs[regPCH], pregs[regPCL]} <= 
                {pregs[regPCH], pregs[regPCL]} + 16'd1;
            phase <= OP_FETCH1;
        end

        // =====================================================================
        // Fallback
        // =====================================================================
        default: phase <= OP_FETCH1;

        endcase // phase
    end // not RESET
end // always


wire [0:7] r_regPCL = pregs[0];
wire [0:7] r_regPCH = pregs[1];
wire [0:7] r_regA = pregs[2];
wire [0:7] r_regB = pregs[3];
wire [0:7] r_regC = pregs[4];
wire [0:7] r_regD = pregs[5];
wire [0:7] r_regPOINTERL = pregs[6];
wire [0:7] r_regPOINTERH = pregs[7];
wire [0:7] r_regSTATUSL = pregs[8];
wire [0:7] r_regSTATUSH = pregs[9];
wire [0:7] r_regIR = pregs[10];
wire [0:7] r_regJUMPL = pregs[12];
wire [0:7] r_regJUMPH = pregs[13];
wire [0:7] r_regE = pregs[14];
wire [0:7] r_regF = pregs[15];


endmodule

src/cpu_tb.v
`define SIM 1
`include "myCPU.v"

module cpu_tb();

    // -------------------------------------------------------------------------
    // CLOCK AND RESET
    // -------------------------------------------------------------------------
    reg CLK = 0;
    reg RESET = 1;

    //always #5 CLK = ~CLK;   // 100MHz clock (10ns period)
    always #2 CLK = ~CLK;   // 500MHz clock (2ns period)

    // -------------------------------------------------------------------------
    // CPU I/O WIRES
    // -------------------------------------------------------------------------
    wire [15:0] AB;
    wire  [7:0] DO;
    wire  [7:0] DI;
    wire        RW;

    // -------------------------------------------------------------------------
    // Instantiate your CPU
    // -------------------------------------------------------------------------
    myCPU uut (
        .CLK(CLK),
        .RESET(RESET),
        .DI(DI),
        .AB(AB),
        .DO(DO),
        .RW(RW)
    );

    // -------------------------------------------------------------------------
    // Simple test RAM (64KB)
    // In your CPU, reads happen with RW = 0 and writes with RW = 1
    // -------------------------------------------------------------------------
    reg [7:0] MEM [0:65535];

    assign DI = (RW == 0) ? MEM[AB] : 8'hZZ;

    integer i;    

    always @(posedge CLK) begin
        if (RW == 1) begin
            MEM[AB] <= DO;
        end
    end


    // =========================================================================
    // INITIALIZATION & TEST CONTROL
    // =========================================================================
    initial begin
        $display("===== CPU TEST START =====");
        $dumpfile("cpu_test.vcd");
        $dumpvars(0, cpu_tb);

        $readmemh("counter.hex", MEM);

        // Hold reset for 5 cycles
        repeat (5) @(posedge CLK);
        RESET = 0;

        // Run simulation for 5000ns
        repeat (500) @(posedge CLK);


        $display("===== CPU TEST FINISHED =====");
        $finish;
    end

endmodule

src/cpu_test.vcd
$date
	Tue Nov 25 16:10:06 2025
$end
$version
	Icarus Verilog
$end
$timescale
	1s
$end
$scope module cpu_tb $end
$var wire 1 ! RW $end
$var wire 8 " DO [7:0] $end
$var wire 8 # DI [7:0] $end
$var wire 16 $ AB [15:0] $end
$var reg 1 % CLK $end
$var reg 1 & RESET $end
$scope module uut $end
$var wire 1 % CLK $end
$var wire 8 ' DI [7:0] $end
$var wire 1 & RESET $end
$var wire 8 ( r_regA [0:7] $end
$var wire 8 ) r_regB [0:7] $end
$var wire 8 * r_regC [0:7] $end
$var wire 8 + r_regD [0:7] $end
$var wire 8 , r_regE [0:7] $end
$var wire 8 - r_regF [0:7] $end
$var wire 8 . r_regIR [0:7] $end
$var wire 8 / r_regJUMPH [0:7] $end
$var wire 8 0 r_regJUMPL [0:7] $end
$var wire 8 1 r_regPCH [0:7] $end
$var wire 8 2 r_regPCL [0:7] $end
$var wire 8 3 r_regPOINTERH [0:7] $end
$var wire 8 4 r_regPOINTERL [0:7] $end
$var wire 8 5 r_regSTATUSH [0:7] $end
$var wire 8 6 r_regSTATUSL [0:7] $end
$var parameter 3 7 INSTR_ADD $end
$var parameter 3 8 INSTR_AND $end
$var parameter 3 9 INSTR_CHG $end
$var parameter 3 : INSTR_JP $end
$var parameter 3 ; INSTR_LD $end
$var parameter 3 < INSTR_NOT $end
$var parameter 3 = INSTR_SET $end
$var parameter 3 > INSTR_ST $end
$var parameter 8 ? OP_FETCH1 $end
$var parameter 8 @ OP_FETCH2 $end
$var parameter 8 A OP_MEMREAD $end
$var parameter 8 B OP_MEMWRITE $end
$var parameter 1 C READ $end
$var parameter 1 D WRITE $end
$var parameter 4 E regA $end
$var parameter 4 F regB $end
$var parameter 4 G regC $end
$var parameter 4 H regD $end
$var parameter 4 I regE $end
$var parameter 4 J regF $end
$var parameter 4 K regIR $end
$var parameter 4 L regJUMPH $end
$var parameter 4 M regJUMPL $end
$var parameter 4 N regPCH $end
$var parameter 4 O regPCL $end
$var parameter 4 P regPOINTERH $end
$var parameter 4 Q regPOINTERL $end
$var parameter 4 R regSTATUSH $end
$var parameter 4 S regSTATUSL $end
$var parameter 3 T statusRegC $end
$var parameter 3 U statusRegZ $end
$var reg 16 V AB [15:0] $end
$var reg 8 W DO [7:0] $end
$var reg 1 ! RW $end
$var reg 1 X carry $end
$var reg 3 Y phase [2:0] $end
$var reg 4 Z selectedReg [3:0] $end
$var reg 9 [ sum9 [8:0] $end
$var reg 8 \ tmp [7:0] $end
$upscope $end
$upscope $end
$enddefinitions $end
$comment Show the parameter values. $end
$dumpall
b0 U
b1 T
b1000 S
b1001 R
b110 Q
b111 P
b0 O
b1 N
b1100 M
b1101 L
b1010 K
b1111 J
b1110 I
b101 H
b100 G
b11 F
b10 E
1D
0C
b11 B
b10 A
b1 @
b0 ?
b10 >
b0 =
b101 <
b1 ;
b110 :
b111 9
b11 8
b100 7
$end
#0
$dumpvars
bx \
bx [
bx Z
bx Y
xX
bx W
bx V
bx 6
bx 5
bx 4
bx 3
bx 2
bx 1
bx 0
bx /
bx .
bx -
bx ,
bx +
bx *
bx )
bx (
bx '
1&
0%
bx $
bx #
bx "
x!
$end
#2
b1100000 #
b1100000 '
b0 Z
0X
0!
b0 "
b0 W
b0 $
b0 V
b0 Y
b0 -
b0 ,
b0 /
b0 0
b0 .
b0 5
b0 6
b0 4
b0 +
b0 *
b0 )
b0 (
b0 1
b0 2
1%
#4
0%
#6
1%
#8
0%
#10
1%
#12
0%
#14
1%
#16
0%
#18
b1 Y
0&
1%
#20
0%
#22
b0 #
b0 '
b10 Y
b1 $
b1 V
b1 2
b110 Z
b1100000 .
1%
#24
0%
#26
b0 Y
b10 2
1%
#28
0%
#30
b1110000 #
b1110000 '
b1 Y
b10 $
b10 V
1%
#32
0%
#34
b100000 #
b100000 '
b10 Y
b11 $
b11 V
b11 2
b111 Z
b1110000 .
1%
#36
0%
#38
b0 Y
b100 2
b100000 3
1%
#40
0%
#42
b11010000 #
b11010000 '
b1 Y
b100 $
b100 V
1%
#44
0%
#46
b0 #
b0 '
b10 Y
b101 $
b101 V
b101 2
b1101 Z
b11010000 .
1%
#48
0%
#50
b0 Y
b110 2
1%
#52
0%
#54
b11000000 #
b11000000 '
b1 Y
b110 $
b110 V
1%
#56
0%
#58
b1100 #
b1100 '
b10 Y
b111 $
b111 V
b111 2
b1100 Z
b11000000 .
1%
#60
0%
#62
b0 Y
b1000 2
b1100 0
1%
#64
0%
#66
b110000 #
b110000 '
b1 Y
b1000 $
b1000 V
1%
#68
0%
#70
b1 #
b1 '
b10 Y
b1001 $
b1001 V
b1001 2
b11 Z
b110000 .
1%
#72
0%
#74
b0 Y
b1010 2
b1 )
1%
#76
0%
#78
b100000 #
b100000 '
b1 Y
b1010 $
b1010 V
1%
#80
0%
#82
b0 #
b0 '
b10 Y
b1011 $
b1011 V
b1011 2
b10 Z
b100000 .
1%
#84
0%
#86
b0 Y
b1100 2
1%
#88
0%
#90
b100010 #
b100010 '
b1 Y
b1100 $
b1100 V
1%
#92
0%
#94
bz #
bz '
b11 Y
1!
b10000000000000 $
b10000000000000 V
b100010 .
1%
#96
0%
#98
b0 Y
b1101 2
1%
#100
0%
#102
b110100 #
b110100 '
b1 Y
0!
b1101 $
b1101 V
1%
#104
0%
#106
b0 Y
b1110 2
b1 (
b110100 .
b1 [
1%
#108
0%
#110
b100011 #
b100011 '
b1 Y
b1110 $
b1110 V
1%
#112
0%
#114
b0 Y
b1111 2
b100011 .
1%
#116
0%
#118
b10000000 #
b10000000 '
b1 Y
b1111 $
b1111 V
1%
#120
0%
#122
b0 #
b0 '
b10 Y
b10000 $
b10000 V
b10000 2
b1000 Z
b10000000 .
1%
#124
0%
#126
b0 Y
b10001 2
1%
#128
0%
#130
b110 #
b110 '
b1 Y
b10001 $
b10001 V
1%
#132
0%
#134
b0 Y
b1100 2
b110 .
1%
#136
0%
#138
b100010 #
b100010 '
b1 Y
b1100 $
b1100 V
1%
#140
0%
#142
bz #
bz '
b11 Y
b1 "
b1 W
1!
b10000000000000 $
b10000000000000 V
b100010 .
1%
#144
0%
#146
b0 Y
b1101 2
1%
#148
0%
#150
b110100 #
b110100 '
b1 Y
0!
b1101 $
b1101 V
1%
#152
0%
#154
b0 Y
b1110 2
b10 (
b110100 .
b10 [
1%
#156
0%
#158
b100011 #
b100011 '
b1 Y
b1110 $
b1110 V
1%
#160
0%
#162
b0 Y
b1111 2
b100011 .
1%
#164
0%
#166
b10000000 #
b10000000 '
b1 Y
b1111 $
b1111 V
1%
#168
0%
#170
b0 #
b0 '
b10 Y
b10000 $
b10000 V
b10000 2
b10000000 .
1%
#172
0%
#174
b0 Y
b10001 2
1%
#176
0%
#178
b110 #
b110 '
b1 Y
b10001 $
b10001 V
1%
#180
0%
#182
b0 Y
b1100 2
b110 .
1%
#184
0%
#186
b100010 #
b100010 '
b1 Y
b1100 $
b1100 V
1%
#188
0%
#190
bz #
bz '
b11 Y
b10 "
b10 W
1!
b10000000000000 $
b10000000000000 V
b100010 .
1%
#192
0%
#194
b0 Y
b1101 2
1%
#196
0%
#198
b110100 #
b110100 '
b1 Y
0!
b1101 $
b1101 V
1%
#200
0%
#202
b0 Y
b1110 2
b11 (
b110100 .
b11 [
1%
#204
0%
#206
b100011 #
b100011 '
b1 Y
b1110 $
b1110 V
1%
#208
0%
#210
b0 Y
b1111 2
b100011 .
1%
#212
0%
#214
b10000000 #
b10000000 '
b1 Y
b1111 $
b1111 V
1%
#216
0%
#218
b0 #
b0 '
b10 Y
b10000 $
b10000 V
b10000 2
b10000000 .
1%
#220
0%
#222
b0 Y
b10001 2
1%
#224
0%
#226
b110 #
b110 '
b1 Y
b10001 $
b10001 V
1%
#228
0%
#230
b0 Y
b1100 2
b110 .
1%
#232
0%
#234
b100010 #
b100010 '
b1 Y
b1100 $
b1100 V
1%
#236
0%
#238
bz #
bz '
b11 Y
b11 "
b11 W
1!
b10000000000000 $
b10000000000000 V
b100010 .
1%
#240
0%
#242
b0 Y
b1101 2
1%
#244
0%
#246
b110100 #
b110100 '
b1 Y
0!
b1101 $
b1101 V
1%
#248
0%
#250
b0 Y
b1110 2
b100 (
b110100 .
b100 [
1%
#252
0%
#254
b100011 #
b100011 '
b1 Y
b1110 $
b1110 V
1%
#256
0%
#258
b0 Y
b1111 2
b100011 .
1%
#260
0%
#262
b10000000 #
b10000000 '
b1 Y
b1111 $
b1111 V
1%
#264
0%
#266
b0 #
b0 '
b10 Y
b10000 $
b10000 V
b10000 2
b10000000 .
1%
#268
0%
#270
b0 Y
b10001 2
1%
#272
0%
#274
b110 #
b110 '
b1 Y
b10001 $
b10001 V
1%
#276
0%
#278
b0 Y
b1100 2
b110 .
1%
#280
0%
#282
b100010 #
b100010 '
b1 Y
b1100 $
b1100 V
1%
#284
0%
#286
bz #
bz '
b11 Y
b100 "
b100 W
1!
b10000000000000 $
b10000000000000 V
b100010 .
1%
#288
0%
#290
b0 Y
b1101 2
1%
#292
0%
#294
b110100 #
b110100 '
b1 Y
0!
b1101 $
b1101 V
1%
#296
0%
#298
b0 Y
b1110 2
b101 (
b110100 .
b101 [
1%
#300
0%
#302
b100011 #
b100011 '
b1 Y
b1110 $
b1110 V
1%
#304
0%
#306
b0 Y
b1111 2
b100011 .
1%
#308
0%
#310
b10000000 #
b10000000 '
b1 Y
b1111 $
b1111 V
1%
#312
0%
#314
b0 #
b0 '
b10 Y
b10000 $
b10000 V
b10000 2
b10000000 .
1%
#316
0%
#318
b0 Y
b10001 2
1%
#320
0%
#322
b110 #
b110 '
b1 Y
b10001 $
b10001 V
1%
#324
0%
#326
b0 Y
b1100 2
b110 .
1%
#328
0%
#330
b100010 #
b100010 '
b1 Y
b1100 $
b1100 V
1%
#332
0%
#334
bz #
bz '
b11 Y
b101 "
b101 W
1!
b10000000000000 $
b10000000000000 V
b100010 .
1%
#336
0%
#338
b0 Y
b1101 2
1%
#340
0%
#342
b110100 #
b110100 '
b1 Y
0!
b1101 $
b1101 V
1%
#344
0%
#346
b0 Y
b1110 2
b110 (
b110100 .
b110 [
1%
#348
0%
#350
b100011 #
b100011 '
b1 Y
b1110 $
b1110 V
1%
#352
0%
#354
b0 Y
b1111 2
b100011 .
1%
#356
0%
#358
b10000000 #
b10000000 '
b1 Y
b1111 $
b1111 V
1%
#360
0%
#362
b0 #
b0 '
b10 Y
b10000 $
b10000 V
b10000 2
b10000000 .
1%
#364
0%
#366
b0 Y
b10001 2
1%
#368
0%
#370
b110 #
b110 '
b1 Y
b10001 $
b10001 V
1%
#372
0%
#374
b0 Y
b1100 2
b110 .
1%
#376
0%
#378
b100010 #
b100010 '
b1 Y
b1100 $
b1100 V
1%
#380
0%
#382
bz #
bz '
b11 Y
b110 "
b110 W
1!
b10000000000000 $
b10000000000000 V
b100010 .
1%
#384
0%
#386
b0 Y
b1101 2
1%
#388
0%
#390
b110100 #
b110100 '
b1 Y
0!
b1101 $
b1101 V
1%
#392
0%
#394
b0 Y
b1110 2
b111 (
b110100 .
b111 [
1%
#396
0%
#398
b100011 #
b100011 '
b1 Y
b1110 $
b1110 V
1%
#400
0%
#402
b0 Y
b1111 2
b100011 .
1%
#404
0%
#406
b10000000 #
b10000000 '
b1 Y
b1111 $
b1111 V
1%
#408
0%
#410
b0 #
b0 '
b10 Y
b10000 $
b10000 V
b10000 2
b10000000 .
1%
#412
0%
#414
b0 Y
b10001 2
1%
#416
0%
#418
b110 #
b110 '
b1 Y
b10001 $
b10001 V
1%
#420
0%
#422
b0 Y
b1100 2
b110 .
1%
#424
0%
#426
b100010 #
b100010 '
b1 Y
b1100 $
b1100 V
1%
#428
0%
#430
bz #
bz '
b11 Y
b111 "
b111 W
1!
b10000000000000 $
b10000000000000 V
b100010 .
1%
#432
0%
#434
b0 Y
b1101 2
1%
#436
0%
#438
b110100 #
b110100 '
b1 Y
0!
b1101 $
b1101 V
1%
#440
0%
#442
b0 Y
b1110 2
b1000 (
b110100 .
b1000 [
1%
#444
0%
#446
b100011 #
b100011 '
b1 Y
b1110 $
b1110 V
1%
#448
0%
#450
b0 Y
b1111 2
b100011 .
1%
#452
0%
#454
b10000000 #
b10000000 '
b1 Y
b1111 $
b1111 V
1%
#456
0%
#458
b0 #
b0 '
b10 Y
b10000 $
b10000 V
b10000 2
b10000000 .
1%
#460
0%
#462
b0 Y
b10001 2
1%
#464
0%
#466
b110 #
b110 '
b1 Y
b10001 $
b10001 V
1%
#468
0%
#470
b0 Y
b1100 2
b110 .
1%
#472
0%
#474
b100010 #
b100010 '
b1 Y
b1100 $
b1100 V
1%
#476
0%
#478
bz #
bz '
b11 Y
b1000 "
b1000 W
1!
b10000000000000 $
b10000000000000 V
b100010 .
1%
#480
0%
#482
b0 Y
b1101 2
1%
#484
0%
#486
b110100 #
b110100 '
b1 Y
0!
b1101 $
b1101 V
1%
#488
0%
#490
b0 Y
b1110 2
b1001 (
b110100 .
b1001 [
1%
#492
0%
#494
b100011 #
b100011 '
b1 Y
b1110 $
b1110 V
1%
#496
0%
#498
b0 Y
b1111 2
b100011 .
1%
#500
0%
#502
b10000000 #
b10000000 '
b1 Y
b1111 $
b1111 V
1%
#504
0%
#506
b0 #
b0 '
b10 Y
b10000 $
b10000 V
b10000 2
b10000000 .
1%
#508
0%
#510
b0 Y
b10001 2
1%
#512
0%
#514
b110 #
b110 '
b1 Y
b10001 $
b10001 V
1%
#516
0%
#518
b0 Y
b1100 2
b110 .
1%
#520
0%
#522
b100010 #
b100010 '
b1 Y
b1100 $
b1100 V
1%
#524
0%
#526
bz #
bz '
b11 Y
b1001 "
b1001 W
1!
b10000000000000 $
b10000000000000 V
b100010 .
1%
#528
0%
#530
b0 Y
b1101 2
1%
#532
0%
#534
b110100 #
b110100 '
b1 Y
0!
b1101 $
b1101 V
1%
#536
0%
#538
b0 Y
b1110 2
b1010 (
b110100 .
b1010 [
1%
#540
0%
#542
b100011 #
b100011 '
b1 Y
b1110 $
b1110 V
1%
#544
0%
#546
b0 Y
b1111 2
b100011 .
1%
#548
0%
#550
b10000000 #
b10000000 '
b1 Y
b1111 $
b1111 V
1%
#552
0%
#554
b0 #
b0 '
b10 Y
b10000 $
b10000 V
b10000 2
b10000000 .
1%
#556
0%
#558
b0 Y
b10001 2
1%
#560
0%
#562
b110 #
b110 '
b1 Y
b10001 $
b10001 V
1%
#564
0%
#566
b0 Y
b1100 2
b110 .
1%
#568
0%
#570
b100010 #
b100010 '
b1 Y
b1100 $
b1100 V
1%
#572
0%
#574
bz #
bz '
b11 Y
b1010 "
b1010 W
1!
b10000000000000 $
b10000000000000 V
b100010 .
1%
#576
0%
#578
b0 Y
b1101 2
1%
#580
0%
#582
b110100 #
b110100 '
b1 Y
0!
b1101 $
b1101 V
1%
#584
0%
#586
b0 Y
b1110 2
b1011 (
b110100 .
b1011 [
1%
#588
0%
#590
b100011 #
b100011 '
b1 Y
b1110 $
b1110 V
1%
#592
0%
#594
b0 Y
b1111 2
b100011 .
1%
#596
0%
#598
b10000000 #
b10000000 '
b1 Y
b1111 $
b1111 V
1%
#600
0%
#602
b0 #
b0 '
b10 Y
b10000 $
b10000 V
b10000 2
b10000000 .
1%
#604
0%
#606
b0 Y
b10001 2
1%
#608
0%
#610
b110 #
b110 '
b1 Y
b10001 $
b10001 V
1%
#612
0%
#614
b0 Y
b1100 2
b110 .
1%
#616
0%
#618
b100010 #
b100010 '
b1 Y
b1100 $
b1100 V
1%
#620
0%
#622
bz #
bz '
b11 Y
b1011 "
b1011 W
1!
b10000000000000 $
b10000000000000 V
b100010 .
1%
#624
0%
#626
b0 Y
b1101 2
1%
#628
0%
#630
b110100 #
b110100 '
b1 Y
0!
b1101 $
b1101 V
1%
#632
0%
#634
b0 Y
b1110 2
b1100 (
b110100 .
b1100 [
1%
#636
0%
#638
b100011 #
b100011 '
b1 Y
b1110 $
b1110 V
1%
#640
0%
#642
b0 Y
b1111 2
b100011 .
1%
#644
0%
#646
b10000000 #
b10000000 '
b1 Y
b1111 $
b1111 V
1%
#648
0%
#650
b0 #
b0 '
b10 Y
b10000 $
b10000 V
b10000 2
b10000000 .
1%
#652
0%
#654
b0 Y
b10001 2
1%
#656
0%
#658
b110 #
b110 '
b1 Y
b10001 $
b10001 V
1%
#660
0%
#662
b0 Y
b1100 2
b110 .
1%
#664
0%
#666
b100010 #
b100010 '
b1 Y
b1100 $
b1100 V
1%
#668
0%
#670
bz #
bz '
b11 Y
b1100 "
b1100 W
1!
b10000000000000 $
b10000000000000 V
b100010 .
1%
#672
0%
#674
b0 Y
b1101 2
1%
#676
0%
#678
b110100 #
b110100 '
b1 Y
0!
b1101 $
b1101 V
1%
#680
0%
#682
b0 Y
b1110 2
b1101 (
b110100 .
b1101 [
1%
#684
0%
#686
b100011 #
b100011 '
b1 Y
b1110 $
b1110 V
1%
#688
0%
#690
b0 Y
b1111 2
b100011 .
1%
#692
0%
#694
b10000000 #
b10000000 '
b1 Y
b1111 $
b1111 V
1%
#696
0%
#698
b0 #
b0 '
b10 Y
b10000 $
b10000 V
b10000 2
b10000000 .
1%
#700
0%
#702
b0 Y
b10001 2
1%
#704
0%
