src/myCPU.v
module myCPU (
// ============================================================================
// myCPU.v   (Heavily commented / educational version)
// ----------------------------------------------------------------------------
// A minimalistic custom CPU with:
//
//   • 16 general-purpose 8-bit registers (pregs[0..15])
//   • 16-bit program counter (PCH:PCL)
//   • 8-bit instruction register (IR)
//   • 16-bit pointer register (POINTERH:POINTERL)
//   • simple fetch → decode → optional memory → execute micro-phases
//   • instructions encoded inside DI[2:0] (3-bit opcode)
//   • optional register index in DI[7:4]
//
// The CPU performs **one instruction fetch per two cycles**:
//
//   OP_FETCH1 → OP_FETCH2 → (optional memory phase) → OP_FETCH1...
//
// Memory interface:
//   AB  = 16-bit address bus
//   DI  = 8-bit data input from memory
//   DO  = 8-bit data output to memory
//   RW  = read(0) or write(1)
//
// This version includes EXCESSIVE comments for maximum clarity.
// ============================================================================ss
    // CPU clock and reset
    input  wire        CLK,      // rising-edge active clock
    input  wire        RESET,    // reset = initialize CPU

    // Memory interface
    input  wire [7:0]  DI,       // data read from memory
    output reg  [15:0] AB,       // address bus
    output reg  [7:0]  DO,       // data to memory (on write)
    output reg         RW        // READ=0, WRITE=1
);

// ============================================================================
// CPU MICRO-PHASE STATES
// These are *not* instructions — they are internal CPU pipeline microsteps.
// ============================================================================

parameter OP_FETCH1   = 8'h00;   // place PC on address bus, request memory read
parameter OP_FETCH2   = 8'h01;   // instruction arrives in DI → decode opcode
parameter OP_MEMREAD  = 8'h02;   // load register from memory
parameter OP_MEMWRITE = 8'h03;   // write register to memory

reg [2:0] phase;                 // current micro-phase

// ============================================================================
// CPU REGISTER FILE LAYOUT  (pregs[0..15])
// ============================================================================
// 16 8-bit registers. Index meanings:
//
//    0  = PCL        (program counter low byte)
//    1  = PCH        (program counter high byte)
//    2  = A          (accumulator)
//    3  = B
//    4  = C
//    5  = D
//    6  = POINTERL   (low byte of memory pointer)
//    7  = POINTERH   (high byte of memory pointer)
//    8  = STATUSL    (flags: Z, C, ...)
//    9  = STATUSH    (reserved)
//    A  = IR         (instruction register)
//    C  = JUMPL      (jump vector low)
//    D  = JUMPH      (jump vector high)
//    E  = E          (free)
//    F  = F          (free)
//
// Registers B–F are available to user code.
// ============================================================================

parameter regPCL       = 4'h0;
parameter regPCH       = 4'h1;
parameter regA         = 4'h2;
parameter regB         = 4'h3;
parameter regC         = 4'h4;
parameter regD         = 4'h5;
parameter regPOINTERL  = 4'h6;
parameter regPOINTERH  = 4'h7;
parameter regSTATUSL   = 4'h8;
parameter regSTATUSH   = 4'h9;
parameter regIR        = 4'hA;
parameter regJUMPL     = 4'hC;
parameter regJUMPH     = 4'hD;
parameter regE         = 4'hE;
parameter regF         = 4'hF;

// ============================================================================
// STATUS REGISTER BIT DEFINITIONS
// ---------------------------------------------------------------------------
// STATUSL bit 0 = Z  (Zero flag)
// STATUSL bit 1 = C  (Carry flag)
// ============================================================================

parameter statusRegZ   = 3'd0;
parameter statusRegC   = 3'd1;

// ============================================================================
// 16-entry register file
// ============================================================================

reg [7:0] pregs [0:15];      // 16 general-purpose registers

reg        carry;            // internal carry flag (not always used)
reg [8:0] sum9;
reg [7:0] tmp;
reg [3:0]  selectedReg;      // used for memory load target register

// ============================================================================
// Memory direction constants
// ============================================================================
parameter READ  = 1'b0;
parameter WRITE = 1'b1;

// ============================================================================
// OPCODE DEFINITIONS (3-bit opcode in DI[2:0])
// Leading upper nibble (DI[7:4]) often encodes a register index.
// ============================================================================

parameter INSTR_SET  = 3'h0;   // SET A = (next byte)
parameter INSTR_LDA  = 3'h1;   // LDA: reg[DI[7:4]] = mem[pointer]
parameter INSTR_STA  = 3'h2;   // STA: mem[pointer] = reg[DI[7:4]]
parameter INSTR_AND  = 3'h3;   // A = A & R
parameter INSTR_ADD  = 3'h4;   // A = A + R (Z,C flags)
parameter INSTR_NOT  = 3'h5;   // R = ~R
parameter INSTR_JPZ  = 3'h6;   // if Z=1 then jump to {JUMPH,JUMPL}
parameter INSTR_CHG  = 3'h7;   // swap A ↔ R

integer i;

// ============================================================================
// MAIN CPU PROCESS
// Executes one micro-operation per clock.
// ============================================================================
always @(posedge CLK) begin

    // =========================================================================
    // RESET PHASE
    // =========================================================================
    if (RESET) begin
        // Clear all registers for deterministic startup
        
        pregs[0] <= 8'h00;
        pregs[1] <= 8'h00;
        pregs[2] <= 8'h00;
        pregs[3] <= 8'h00;
        pregs[4] <= 8'h00;
        pregs[5] <= 8'h00;
        pregs[6] <= 8'h00;
        pregs[8] <= 8'h00;
        pregs[9] <= 8'h00;
        pregs[10] <= 8'h00;
        pregs[11] <= 8'h00;
        pregs[12] <= 8'h00;
        pregs[13] <= 8'h00;
        pregs[14] <= 8'h00;
        pregs[15] <= 8'h00;


        // Start fetching from address 0x0000
        phase <= OP_FETCH1;

        // Initialize bus state
        AB    <= 16'h0000;
        DO    <= 8'h00;
        RW    <= READ;
        carry <= 1'b0;
        selectedReg <= 4'h0;
    end 
    else begin

        // =====================================================================
        // CPU MICRO-PHASE STATE MACHINE
        // =====================================================================
        case (phase)

        // =====================================================================
        // OP_FETCH1 — Place the PC on the address bus and request memory read
        // =====================================================================
        OP_FETCH1: begin
            AB <= {pregs[regPCH], pregs[regPCL]};  // address = PC
            RW <= READ;                            // request read
            phase <= OP_FETCH2;                    // next phase: fetch instruction
        end

        // =====================================================================
        // OP_FETCH2 — CPU receives instruction byte in DI
        // =====================================================================
        OP_FETCH2: begin
            pregs[regIR] <= DI;          // Store instruction byte into IR

            // Decode opcode (lower 3 bits)
            case (DI[2:0])

                // ---------------------------------------------------------------------
                // SET — Load immediate value into register A
                //   Format:    [ rrrr 0000 ]
                // ---------------------------------------------------------------------
                INSTR_SET: begin
                    selectedReg <= DI[7:4];    // load immediate selected reg
                    // Increase PC to next byte (the immediate)
                    {pregs[regPCH], pregs[regPCL]} <= 
                        {pregs[regPCH], pregs[regPCL]} + 16'd1;

                    // Memory read for the immediate byte
                    AB <= {pregs[regPCH], pregs[regPCL]} + 16'd1;
                    RW <= READ;
                    phase <= OP_MEMREAD;
                end

                // ---------------------------------------------------------------------
                // LDA — Load register from memory at pointer address
                // ---------------------------------------------------------------------
                INSTR_LDA: begin
                    selectedReg <= DI[7:4];                // which register to load
                    AB <= {pregs[regPOINTERH], pregs[regPOINTERL]};
                    RW <= READ;
                    phase <= OP_MEMREAD;
                end

                // ---------------------------------------------------------------------
                // STA — Store register into memory at pointer address
                // ---------------------------------------------------------------------
                INSTR_STA: begin
                    AB <= {pregs[regPOINTERH], pregs[regPOINTERL]};
                    RW <= WRITE;
                    DO <= pregs[DI[7:4]];                  // write selected register
                    phase <= OP_MEMWRITE;
                end

                // ---------------------------------------------------------------------
                // AND — A = A & reg[R]
                // ---------------------------------------------------------------------
                INSTR_AND: begin
                    pregs[regA] <= pregs[regA] & pregs[DI[7:4]];
                    // Update Z flag
                    pregs[regSTATUSL][statusRegZ] <= 
                        ((pregs[regA] & pregs[DI[7:4]]) == 8'h00);
                    // Advance PC
                    {pregs[regPCH], pregs[regPCL]} <= 
                        {pregs[regPCH], pregs[regPCL]} + 16'd1;
                    phase <= OP_FETCH1;
                end

                // ---------------------------------------------------------------------
                // ADD — A = A + reg[R], update C,Z
                // ---------------------------------------------------------------------
                INSTR_ADD: begin
                    sum9 = {1'b0, pregs[regA]} + {1'b0, pregs[DI[7:4]]};
                    pregs[regA] <= sum9[7:0];
                    pregs[regSTATUSL][statusRegC] <= sum9[8];
                    pregs[regSTATUSL][statusRegZ] <= (sum9[7:0] == 8'h00);
                    {pregs[regPCH], pregs[regPCL]} <= 
                        {pregs[regPCH], pregs[regPCL]} + 16'd1;
                    phase <= OP_FETCH1;
                end

                // ---------------------------------------------------------------------
                // NOT — reg[R] = ~reg[R]
                // ---------------------------------------------------------------------
                INSTR_NOT: begin
                    pregs[DI[7:4]] <= ~pregs[DI[7:4]];
                    {pregs[regPCH], pregs[regPCL]} <= 
                        {pregs[regPCH], pregs[regPCL]} + 16'd1;
                    phase <= OP_FETCH1;
                end

                // ---------------------------------------------------------------------
                // JPZ — Jump if Zero flag set
                // ---------------------------------------------------------------------
                INSTR_JPZ: begin
                    if (pregs[regSTATUSL][statusRegZ]) begin
                        pregs[regPCL] <= pregs[regJUMPL];
                        pregs[regPCH] <= pregs[regJUMPH];
                    end
                    else begin
                        {pregs[regPCH], pregs[regPCL]} <= 
                            {pregs[regPCH], pregs[regPCL]} + 16'd1;
                    end
                    phase <= OP_FETCH1;
                end

                // ---------------------------------------------------------------------
                // CHG — Swap A <-> reg[R]
                // ---------------------------------------------------------------------
                INSTR_CHG: begin
                    tmp = pregs[DI[7:4]];
                    pregs[DI[7:4]] <= pregs[regA];
                    pregs[regA] <= tmp;
                    {pregs[regPCH], pregs[regPCL]} <= 
                        {pregs[regPCH], pregs[regPCL]} + 16'd1;
                    phase <= OP_FETCH1;
                end

                // ---------------------------------------------------------------------
                // DEFAULT — Undefined opcode → treat as NOP
                // ---------------------------------------------------------------------
                default: begin
                    {pregs[regPCH], pregs[regPCL]} <= 
                        {pregs[regPCH], pregs[regPCL]} + 16'd1;
                    phase <= OP_FETCH1;
                end
            endcase
        end // OP_FETCH2

        // =====================================================================
        // OP_MEMREAD — Data from memory is in DI → store into selectedReg
        // =====================================================================
        OP_MEMREAD: begin
            pregs[selectedReg] <= DI;
            {pregs[regPCH], pregs[regPCL]} <= 
                {pregs[regPCH], pregs[regPCL]} + 16'd1;
            phase <= OP_FETCH1;
        end

        // =====================================================================
        // OP_MEMWRITE — Write was already issued; just advance PC
        // =====================================================================
        OP_MEMWRITE: begin
            {pregs[regPCH], pregs[regPCL]} <= 
                {pregs[regPCH], pregs[regPCL]} + 16'd1;
            phase <= OP_FETCH1;
        end

        // =====================================================================
        // Fallback
        // =====================================================================
        default: phase <= OP_FETCH1;

        endcase // phase
    end // not RESET
end // always


wire [0:7] r_regPCL = pregs[0];
wire [0:7] r_regPCH = pregs[1];
wire [0:7] r_regA = pregs[2];
wire [0:7] r_regB = pregs[3];
wire [0:7] r_regC = pregs[4];
wire [0:7] r_regD = pregs[5];
wire [0:7] r_regPOINTERL = pregs[6];
wire [0:7] r_regPOINTERH = pregs[7];
wire [0:7] r_regSTATUSL = pregs[8];
wire [0:7] r_regSTATUSH = pregs[9];
wire [0:7] r_regIR = pregs[10];
wire [0:7] r_regJUMPL = pregs[12];
wire [0:7] r_regJUMPH = pregs[13];
wire [0:7] r_regE = pregs[14];
wire [0:7] r_regF = pregs[15];


endmodule

src/cpu_tb.v
`define SIM 1
`include "myCPU.v"

module cpu_tb();

    // -------------------------------------------------------------------------
    // CLOCK AND RESET
    // -------------------------------------------------------------------------
    reg CLK = 0;
    reg RESET = 1;

    //always #5 CLK = ~CLK;   // 100MHz clock (10ns period)
    always #2 CLK = ~CLK;   // 500MHz clock (2ns period)

    // -------------------------------------------------------------------------
    // CPU I/O WIRES
    // -------------------------------------------------------------------------
    wire [15:0] AB;
    wire  [7:0] DO;
    wire  [7:0] DI;
    wire        RW;

    // -------------------------------------------------------------------------
    // Instantiate your CPU
    // -------------------------------------------------------------------------
    myCPU uut (
        .CLK(CLK),
        .RESET(RESET),
        .DI(DI),
        .AB(AB),
        .DO(DO),
        .RW(RW)
    );

    // -------------------------------------------------------------------------
    // Simple test RAM (64KB)
    // In your CPU, reads happen with RW = 0 and writes with RW = 1
    // -------------------------------------------------------------------------
    reg [7:0] MEM [0:65535];

    assign DI = (RW == 0) ? MEM[AB] : 8'hZZ;

    integer i;    

    always @(posedge CLK) begin
        if (RW == 1) begin
            MEM[AB] <= DO;
        end
    end

    // =========================================================================
    // TEST PROGRAM LOADED INTO MEMORY
    //
    // It will:
    //   1. SET A = 0x55
    //   2. LDA B from pointer (pointer set to 0x2000 → contains 0xAA)
    //   3. STA B back to 0x2001
    //   4. AND A with B    (0x55 & 0xAA = 0x00 → zero flag = 1)
    //   5. ADD A with B    (0 + 0xAA = 0xAA)
    //   6. NOT B           ( ~0xAA = 0x55 )
    //   7. JPZ to jumpVector (should not jump now)
    //   8. CHG A ↔ B       (swap)
    //
    // The expected final values are included below.
    // =========================================================================

    task load_program;
    begin

        // Clear memory
        for (i = 0; i < 65536; i = i + 1)
            MEM[i] = 8'h00;

        // --- Write test values in memory ---
        MEM[16'h2000] = 8'hAA;    // value for LDA
        MEM[16'h2001] = 8'h00;    // for STA test

        // ---------------------------------------------------------------------
        // PROGRAM START AT 0x0000
        // ---------------------------------------------------------------------

        //  SET A ← immediate
        MEM[16'h0000] = 8'b0000_0000;  // SET opcode
        MEM[16'h0001] = 8'h00;         // immediate value

        //  CHG A ↔ POINTERL
        MEM[16'h0002] = 8'b0110_0111;  // CHG, R=POINTERL       

        //  SET A ← immediate
        MEM[16'h0003] = 8'b0000_0000;  // SET opcode
        MEM[16'h0004] = 8'h20;         // immediate value

        //  CHG A ↔ POINTERH
        MEM[16'h0005] = 8'b0111_0111;  // CHG, R=POINTERH       

        //  SET A ← immediate
        MEM[16'h0006] = 8'b0000_0000;  // SET opcode
        MEM[16'h0007] = 8'h55;         // immediate value        


        //  LDA B
        MEM[16'h0008] = 8'b0011_0001;  // LDA, register index=3 (B)

        //  STA B
        MEM[16'h0009] = 8'b0011_0010;  // STA, register index=3

        //  AND A with B
        MEM[16'h000A] = 8'b0011_0011;  // AND, R=B

        //  ADD A with B
        MEM[16'h000B] = 8'b0011_0100;  // ADD, R=B

        //  NOT B
        MEM[16'h000C] = 8'b0011_0101;  // NOT, R=B

        //  JPZ
        MEM[16'h000D] = 8'b0000_0110;  // JPZ instruction

        //  CHG A ↔ B
        MEM[16'h000E] = 8'b0011_0111;  // CHG, R=B
    end
    endtask

    // =========================================================================
    // INITIALIZATION & TEST CONTROL
    // =========================================================================
    initial begin
        $display("===== CPU TEST START =====");
        $dumpfile("cpu_test.vcd");
        $dumpvars(0, cpu_tb);

        load_program();

        // Hold reset for 5 cycles
        repeat (5) @(posedge CLK);
        RESET = 0;

        // Run simulation for 5000ns
        repeat (500) @(posedge CLK);

        check_results();

        $display("===== CPU TEST FINISHED =====");
        $finish;
    end

    // =========================================================================
    // CHECK RESULTS
    // =========================================================================

    task expect(input [7:0] val, input [7:0] exp, input [127:0] name);
    begin
        if (val !== exp)
            $display("FAIL: %s expected %h got %h", name, exp, val);
        else
            $display("PASS: %s = %h", name, val);
    end
    endtask

    task check_results;
    begin
        $display("\n===== CHECKING CPU RESULTS =====");

        // Word-by-word checking

        expect(uut.pregs[uut.regA], 8'h55, "NOT swapped A? (final A after swap)");  
        expect(uut.pregs[uut.regB], 8'hAA, "Final B after CHG swap");               
        expect(MEM[16'h2001],      8'hAA, "STA wrote B to memory location 0x2001");

        expect(uut.pregs[uut.regSTATUSL][uut.statusRegZ], 1'b0, "Final Z flag");
        expect(uut.pregs[uut.regSTATUSL][uut.statusRegC], 1'b0, "Final C flag");
    end
    endtask

endmodule

src/cpu_test.vcd
$date
	Mon Nov 24 14:54:47 2025
$end
$version
	Icarus Verilog
$end
$timescale
	1s
$end
$scope module cpu_tb $end
$var wire 1 ! RW $end
$var wire 8 " DO [7:0] $end
$var wire 8 # DI [7:0] $end
$var wire 16 $ AB [15:0] $end
$var reg 1 % CLK $end
$var reg 1 & RESET $end
$var integer 32 ' i [31:0] $end
$scope module uut $end
$var wire 1 % CLK $end
$var wire 8 ( DI [7:0] $end
$var wire 1 & RESET $end
$var wire 8 ) r_regA [0:7] $end
$var wire 8 * r_regB [0:7] $end
$var wire 8 + r_regC [0:7] $end
$var wire 8 , r_regD [0:7] $end
$var wire 8 - r_regE [0:7] $end
$var wire 8 . r_regF [0:7] $end
$var wire 8 / r_regIR [0:7] $end
$var wire 8 0 r_regJUMPH [0:7] $end
$var wire 8 1 r_regJUMPL [0:7] $end
$var wire 8 2 r_regPCH [0:7] $end
$var wire 8 3 r_regPCL [0:7] $end
$var wire 8 4 r_regPOINTERH [0:7] $end
$var wire 8 5 r_regPOINTERL [0:7] $end
$var wire 8 6 r_regSTATUSH [0:7] $end
$var wire 8 7 r_regSTATUSL [0:7] $end
$var parameter 3 8 INSTR_ADD $end
$var parameter 3 9 INSTR_AND $end
$var parameter 3 : INSTR_CHG $end
$var parameter 3 ; INSTR_JPZ $end
$var parameter 3 < INSTR_LDA $end
$var parameter 3 = INSTR_NOT $end
$var parameter 3 > INSTR_SET $end
$var parameter 3 ? INSTR_STA $end
$var parameter 8 @ OP_FETCH1 $end
$var parameter 8 A OP_FETCH2 $end
$var parameter 8 B OP_MEMREAD $end
$var parameter 8 C OP_MEMWRITE $end
$var parameter 1 D READ $end
$var parameter 1 E WRITE $end
$var parameter 4 F regA $end
$var parameter 4 G regB $end
$var parameter 4 H regC $end
$var parameter 4 I regD $end
$var parameter 4 J regE $end
$var parameter 4 K regF $end
$var parameter 4 L regIR $end
$var parameter 4 M regJUMPH $end
$var parameter 4 N regJUMPL $end
$var parameter 4 O regPCH $end
$var parameter 4 P regPCL $end
$var parameter 4 Q regPOINTERH $end
$var parameter 4 R regPOINTERL $end
$var parameter 4 S regSTATUSH $end
$var parameter 4 T regSTATUSL $end
$var parameter 3 U statusRegC $end
$var parameter 3 V statusRegZ $end
$var reg 16 W AB [15:0] $end
$var reg 8 X DO [7:0] $end
$var reg 1 ! RW $end
$var reg 1 Y carry $end
$var reg 3 Z phase [2:0] $end
$var reg 4 [ selectedReg [3:0] $end
$var reg 9 \ sum9 [8:0] $end
$var reg 8 ] tmp [7:0] $end
$upscope $end
$scope task check_results $end
$upscope $end
$scope task expect $end
$var reg 8 ^ exp [7:0] $end
$var reg 128 _ name [127:0] $end
$var reg 8 ` val [7:0] $end
$upscope $end
$scope task load_program $end
$upscope $end
$upscope $end
$enddefinitions $end
$comment Show the parameter values. $end
$dumpall
b0 V
b1 U
b1000 T
b1001 S
b110 R
b111 Q
b0 P
b1 O
b1100 N
b1101 M
b1010 L
b1111 K
b1110 J
b101 I
b100 H
b11 G
b10 F
1E
0D
b11 C
b10 B
b1 A
b0 @
b10 ?
b0 >
b101 =
b1 <
b110 ;
b111 :
b11 9
b100 8
$end
#0
$dumpvars
bx `
bx _
bx ^
bx ]
bx \
bx [
bx Z
xY
bx X
bx W
bx 7
bx 6
bx 5
bx 4
bx 3
bx 2
bx 1
bx 0
bx /
bx .
bx -
bx ,
bx +
bx *
bx )
bx (
b10000000000000000 '
1&
0%
bx $
bx #
bx "
x!
$end
#2
b0 #
b0 (
b0 [
0Y
0!
b0 "
b0 X
b0 $
b0 W
b0 Z
b0 .
b0 -
b0 0
b0 1
b0 /
b0 6
b0 7
b0 5
b0 ,
b0 +
b0 *
b0 )
b0 2
b0 3
1%
#4
0%
#6
1%
#8
0%
#10
1%
#12
0%
#14
1%
#16
0%
#18
b1 Z
0&
1%
#20
0%
#22
b10 Z
b1 $
b1 W
b1 3
b10 [
1%
#24
0%
#26
b0 Z
b10 3
1%
#28
0%
#30
b1100111 #
b1100111 (
b1 Z
b10 $
b10 W
1%
#32
0%
#34
b0 Z
b11 3
b1100111 /
b0 ]
1%
#36
0%
#38
b0 #
b0 (
b1 Z
b11 $
b11 W
1%
#40
0%
#42
b100000 #
b100000 (
b10 Z
b100 $
b100 W
b100 3
b0 /
1%
#44
0%
#46
b0 Z
b101 3
b100000 )
1%
#48
0%
#50
b1110111 #
b1110111 (
b1 Z
b101 $
b101 W
1%
#52
0%
#54
b0 Z
b110 3
bx )
b100000 4
b1110111 /
bx ]
1%
#56
0%
#58
b0 #
b0 (
b1 Z
b110 $
b110 W
1%
#60
0%
#62
b1010101 #
b1010101 (
b10 Z
b111 $
b111 W
b111 3
b0 /
1%
#64
0%
#66
b0 Z
b1000 3
b1010101 )
1%
#68
0%
#70
b110001 #
b110001 (
b1 Z
b1000 $
b1000 W
1%
#72
0%
#74
b10101010 #
b10101010 (
b10 Z
b10000000000000 $
b10000000000000 W
b11 [
b110001 /
1%
#76
0%
#78
b0 Z
b1001 3
b10101010 *
1%
#80
0%
#82
b110010 #
b110010 (
b1 Z
b1001 $
b1001 W
1%
#84
0%
#86
bz #
bz (
b11 Z
b10101010 "
b10101010 X
1!
b10000000000000 $
b10000000000000 W
b110010 /
1%
#88
0%
#90
b0 Z
b1010 3
1%
#92
0%
#94
b110011 #
b110011 (
b1 Z
0!
b1010 $
b1010 W
1%
#96
0%
#98
b0 Z
b1011 3
b1 7
b0 )
b110011 /
1%
#100
0%
#102
b110100 #
b110100 (
b1 Z
b1011 $
b1011 W
1%
#104
0%
#106
b0 Z
b1100 3
b0 7
b10101010 )
b110100 /
b10101010 \
1%
#108
0%
#110
b110101 #
b110101 (
b1 Z
b1100 $
b1100 W
1%
#112
0%
#114
b0 Z
b1101 3
b1010101 *
b110101 /
1%
#116
0%
#118
b110 #
b110 (
b1 Z
b1101 $
b1101 W
1%
#120
0%
#122
b0 Z
b1110 3
b110 /
1%
#124
0%
#126
b110111 #
b110111 (
b1 Z
b1110 $
b1110 W
1%
#128
0%
#130
b0 Z
b1111 3
b1010101 )
b10101010 *
b110111 /
b1010101 ]
1%
#132
0%
#134
b0 #
b0 (
b1 Z
b1111 $
b1111 W
1%
#136
0%
#138
b10 Z
b10000 $
b10000 W
b10000 3
b10 [
b0 /
1%
#140
0%
#142
b0 Z
b10001 3
b0 )
1%
#144
0%
#146
b1 Z
b10001 $
b10001 W
1%
#148
0%
#150
b10 Z
b10010 $
b10010 W
b10010 3
1%
#152
0%
#154
b0 Z
b10011 3
1%
#156
0%
#158
b1 Z
b10011 $
b10011 W
1%
#160
0%
#162
b10 Z
b10100 $
b10100 W
b10100 3
1%
#164
0%
#166
b0 Z
b10101 3
1%
#168
0%
#170
b1 Z
b10101 $
b10101 W
1%
#172
0%
#174
b10 Z
b10110 $
b10110 W
b10110 3
1%
#176
0%
#178
b0 Z
b10111 3
1%
#180
0%
#182
b1 Z
b10111 $
b10111 W
1%
#184
0%
#186
b10 Z
b11000 $
b11000 W
b11000 3
1%
#188
0%
#190
b0 Z
b11001 3
1%
#192
0%
#194
b1 Z
b11001 $
b11001 W
1%
#196
0%
#198
b10 Z
b11010 $
b11010 W
b11010 3
1%
#200
0%
#202
b0 Z
b11011 3
1%
#204
0%
#206
b1 Z
b11011 $
b11011 W
1%
#208
0%
#210
b10 Z
b11100 $
b11100 W
b11100 3
1%
#212
0%
#214
b0 Z
b11101 3
1%
#216
0%
#218
b1 Z
b11101 $
b11101 W
1%
#220
0%
#222
b10 Z
b11110 $
b11110 W
b11110 3
1%
#224
0%
#226
b0 Z
b11111 3
1%
#228
0%
#230
b1 Z
b11111 $
b11111 W
1%
#232
0%
#234
b10 Z
b100000 $
b100000 W
b100000 3
1%
#236
0%
#238
b0 Z
b100001 3
1%
#240
0%
#242
b1 Z
b100001 $
b100001 W
1%
#244
0%
#246
b10 Z
b100010 $
b100010 W
b100010 3
1%
#248
0%
#250
b0 Z
b100011 3
1%
#252
0%
#254
b1 Z
b100011 $
b100011 W
1%
#256
0%
#258
b10 Z
b100100 $
b100100 W
b100100 3
1%
#260
0%
#262
b0 Z
b100101 3
1%
#264
0%
#266
b1 Z
b100101 $
b100101 W
1%
#268
0%
#270
b10 Z
b100110 $
b100110 W
b100110 3
1%
#272
0%
#274
b0 Z
b100111 3
1%
#276
0%
#278
b1 Z
b100111 $
b100111 W
1%
#280
0%
#282
b10 Z
b101000 $
b101000 W
b101000 3
1%
#284
0%
#286
b0 Z
b101001 3
1%
#288
0%
#290
b1 Z
b101001 $
b101001 W
1%
#292
0%
#294
b10 Z
b101010 $
b101010 W
b101010 3
1%
#296
0%
#298
b0 Z
b101011 3
1%
#300
0%
#302
b1 Z
b101011 $
b101011 W
1%
#304
0%
#306
b10 Z
b101100 $
b101100 W
b101100 3
1%
#308
0%
#310
b0 Z
b101101 3
1%
#312
0%
#314
b1 Z
b101101 $
b101101 W
1%
#316
0%
#318
b10 Z
b101110 $
b101110 W
b101110 3
1%
#320
0%
#322
b0 Z
b101111 3
1%
#324
0%
#326
b1 Z
b101111 $
b101111 W
1%
#328
0%
#330
b10 Z
b110000 $
b110000 W
b110000 3
1%
#332
0%
#334
b0 Z
b110001 3
1%
#336
0%
#338
b1 Z
b110001 $
b110001 W
1%
#340
0%
#342
b10 Z
b110010 $
b110010 W
b110010 3
1%
#344
0%
#346
b0 Z
b110011 3
1%
#348
0%
#350
b1 Z
b110011 $
b110011 W
1%
#352
0%
#354
b10 Z
b110100 $
b110100 W
b110100 3
1%
#356
0%
#358
b0 Z
b110101 3
1%
#360
0%
#362
b1 Z
b110101 $
b110101 W
1%
#364
0%
#366
b10 Z
b110110 $
b110110 W
b110110 3
1%
#368
0%
#370
b0 Z
b110111 3
1%
#372
0%
#374
b1 Z
b110111 $
b110111 W
1%
#376
0%
#378
b10 Z
b111000 $
b111000 W
b111000 3
1%
#380
0%
#382
b0 Z
b111001 3
1%
#384
0%
#386
b1 Z
b111001 $
b111001 W
1%
#388
0%
#390
b10 Z
b111010 $
b111010 W
b111010 3
1%
#392
0%
#394
b0 Z
b111011 3
1%
#396
0%
#398
b1 Z
b111011 $
b111011 W
1%
#400
0%
#402
b10 Z
b111100 $
b111100 W
b111100 3
1%
#404
0%
#406
b0 Z
b111101 3
1%
#408
0%
#410
b1 Z
b111101 $
b111101 W
1%
#412
0%
#414
b10 Z
b111110 $
b111110 W
b111110 3
1%
#416
0%
#418
b0 Z
b111111 3
1%
#420
0%
#422
b1 Z
b111111 $
b111111 W
1%
#424
0%
#426
b10 Z
b1000000 $
b1000000 W
b1000000 3
1%
#428
0%
#430
b0 Z
b1000001 3
1%
#432
0%
#434
b1 Z
b1000001 $
b1000001 W
1%
#436
0%
#438
b10 Z
b1000010 $
b1000010 W
b1000010 3
1%
#440
0%
#442
b0 Z
b1000011 3
1%
#444
0%
#446
b1 Z
b1000011 $
b1000011 W
1%
#448
0%
#450
b10 Z
b1000100 $
b1000100 W
b1000100 3
1%
#452
0%
#454
b0 Z
b1000101 3
1%
#456
0%
#458
b1 Z
b1000101 $
b1000101 W
1%
#460
0%
#462
b10 Z
b1000110 $
b1000110 W
b1000110 3
1%
#464
0%
#466
b0 Z
b1000111 3
1%
#468
0%
#470
b1 Z
b1000111 $
b1000111 W
1%
#472
0%
#474
b10 Z
b1001000 $
b1001000 W
b1001000 3
1%
#476
0%
#478
b0 Z
b1001001 3
1%
#480
0%
#482
b1 Z
b1001001 $
b1001001 W
1%
#484
0%
#486
b10 Z
b1001010 $
b1001010 W
b1001010 3
1%
#488
0%
#490
b0 Z
b1001011 3
1%
#492
0%
#494
b1 Z
b1001011 $
b1001011 W
1%
#496
0%
#498
b10 Z
b1001100 $
b1001100 W
b1001100 3
1%
#500
0%
#502
b0 Z
b1001101 3
1%
#504
0%
#506
b1 Z
b1001101 $
b1001101 W
1%
#508
0%
#510
b10 Z
b1001110 $
b1001110 W
b1001110 3
1%
#512
0%
#514
b0 Z
b1001111 3
1%
#516
0%
#518
b1 Z
b1001111 $
b1001111 W
1%
#520
0%
#522
b10 Z
b1010000 $
b1010000 W
b1010000 3
1%
#524
0%
#526
b0 Z
b1010001 3
1%
#528
0%
#530
b1 Z
b1010001 $
b1010001 W
1%
#532
0%
#534
b10 Z
b1010010 $
b1010010 W
b1010010 3
1%
#536
0%
#538
b0 Z
b1010011 3
1%
#540
0%
#542
b1 Z
b1010011 $
b1010011 W
1%
#544
0%
#546
b10 Z
b1010100 $
b1010100 W
b1010100 3
1%
#548
0%
#550
b0 Z
b1010101 3
1%
#552
0%
#554
b1 Z
b1010101 $
b1010101 W
1%
#556
0%
#558
b10 Z
b1010110 $
b1010110 W
b1010110 3
1%
#560
0%
#562
b0 Z
b1010111 3
1%
#564
0%
#566
b1 Z
b1010111 $
b1010111 W
1%
#568
0%
#570
b10 Z
b1011000 $
b1011000 W
b1011000 3
1%
#572
0%
#574
b0 Z
b1011001 3
1%
#576
0%
#578
b1 Z
b1011001 $
b1011001 W
1%
#580
0%
#582
b10 Z
b1011010 $
b1011010 W
b1011010 3
1%
#584
0%
#586
b0 Z
b1011011 3
1%
#588
0%
#590
b1 Z
b1011011 $
b1011011 W
1%
#592
0%
#594
b10 Z
b1011100 $
b1011100 W
b1011100 3
1%
#596
0%
#598
b0 Z
b1011101 3
1%
#600
0%
#602
b1 Z
b1011101 $
b1011101 W
1%
#604
0%
#606
b10 Z
b1011110 $
b1011110 W
b1011110 3
1%
#608
0%
#610
b0 Z
b1011111 3
1%
#612
0%
#614
b1 Z
b1011111 $
b1011111 W
1%
#616
0%
#618
b10 Z
b1100000 $
b1100000 W
b1100000 3
1%
#620
0%
#622
b0 Z
b1100001 3
1%
#624
0%
#626
b1 Z
b1100001 $
b1100001 W
1%
#628
0%
#630
b10 Z
b1100010 $
b1100010 W
b1100010 3
1%
#632
0%
#634
b0 Z
b1100011 3
1%
#636
0%
#638
b1 Z
b1100011 $
b1100011 W
1%
#640
0%
#642
b10 Z
b1100100 $
b1100100 W
b1100100 3
1%
#644
0%
#646
b0 Z
b1100101 3
1%
#648
0%
#650
b1 Z
b1100101 $
b1100101 W
1%
#652
0%
#654
b10 Z
b1100110 $
b1100110 W
b1100110 3
1%
#656
0%
#658
b0 Z
b1100111 3
1%
#660
0%
#662
b1 Z
b1100111 $
b1100111 W
1%
#664
0%
#666
b10 Z
b1101000 $
b1101000 W
b1101000 3
1%
#668
0%
#670
b0 Z
b1101001 3
1%
#672
0%
#674
b1 Z
b1101001 $
b1101001 W
1%
#676
0%
#678
b10 Z
b1101010 $
b1101010 W
b1101010 3
1%
#680
0%
#682
b0 Z
b1101011 3
1%
#684
0%
#686
b1 Z
b1101011 $
b1101011 W
1%
#688
0%
#690
b10 Z
b1101100 $
b1101100 W
b1101100 3
1%
#692
0%
#694
b0 Z
b1101101 3
1%
#696
0%
